sensirion_sps030/__init__.py
sensirion_sps030/sensirion_error_codes.py
sensirion_sps030/sensirion_sps030.py
sensirion_sps030-0.0.7.dist-info/LICENSE
sensirion_sps030-0.0.7.dist-info/METADATA
sensirion_sps030-0.0.7.dist-info/WHEEL
sensirion_sps030-0.0.7.dist-info/top_level.txt
sensirion_sps030-0.0.7.dist-info/RECORD
