Metadata-Version: 2.1
Name: sensirion-sps030
Version: 0.0.7
Summary: An interface for Sensirion SPS030 particulate matter sensors
Home-page: https://github.com/FEEprojects/sensirion-sps030
Author: Florentin Bulot
Author-email: f.bulot@soton.ac.uk
License: UNKNOWN
Platform: UNKNOWN
Classifier: Programming Language :: Python :: 3
Classifier: License :: OSI Approved :: MIT License
Classifier: Operating System :: OS Independent
Requires-Python: >=3.3, <4
Requires-Dist: pyserial
